example/__init__.py
example/monitor_tasks.py
example/tasks.py
veggie/__init__.py
veggie/monitor.py
veggie/storage.py
veggie/webapp/__init__.py
veggie/webapp/api.py
veggie/webapp/flask_app.py
veggie/webapp/dashboard/__init__.py
veggie/webapp/dashboard/config.py
veggie/webapp/dashboard/header.py
veggie/webapp/dashboard/index.py
veggie/webapp/dashboard/navbar.py
veggie/webapp/dashboard/style.py
veggie/webapp/dashboard/pages/__init__.py
veggie/webapp/dashboard/pages/not_found_404.py
veggie/webapp/dashboard/pages/status.py
veggie/webapp/dashboard/pages/tasks.py
veggie-0.1.12.dist-info/LICENSE
veggie-0.1.12.dist-info/METADATA
veggie-0.1.12.dist-info/WHEEL
veggie-0.1.12.dist-info/top_level.txt
veggie-0.1.12.dist-info/RECORD
