Metadata-Version: 2.1
Name: veggie
Version: 0.1.12
Summary: A tool to monitor and execute Celery tasks
Author: Theodore Tsitsimis
Author-email: th.tsitsimis@gmail.com
Classifier: Development Status :: 3 - Alpha
Classifier: Intended Audience :: Developers
Classifier: Programming Language :: Python :: 3
Classifier: Programming Language :: Python :: 3.11
Classifier: Programming Language :: Python :: 3.12
Classifier: License :: OSI Approved :: MIT License
License-File: LICENSE
Requires-Dist: dash>=2.5.1
Requires-Dist: dash-extensions>=1.0.19
Requires-Dist: dash-mantine-components>=0.15.1
Requires-Dist: dash-iconify
Requires-Dist: loguru
Requires-Dist: celery[redis]
Requires-Dist: humanize
